torch_nets/__init__.py
torch_nets/__version__.py
torch_nets/_augmented_torch_net.py
torch_nets/_decoder.py
torch_nets/_encoder.py
torch_nets/_torch_net.py
torch_nets/core/__init__.py
torch_nets/core/_layer_builder.py
torch_nets/core/_power_space.py
torch_nets/core/config/__init__.py
torch_nets/core/config/_activation_function_config.py
torch_nets/core/config/_config.py
torch_nets/core/config/_layer_wise_attributes_config.py
torch_nets/core/config/_network_structure_config.py
torch_nets/tools/__init__.py
torch_nets/tools/_infer_network_architecture_from_state.py
torch_nets-0.2.0.dist-info/LICENSE
torch_nets-0.2.0.dist-info/METADATA
torch_nets-0.2.0.dist-info/WHEEL
torch_nets-0.2.0.dist-info/top_level.txt
torch_nets-0.2.0.dist-info/RECORD
